agentopia/__init__.py
agentopia/abis/ERC20.json
agentopia/abis/MicroPayment.json
agentopia/abis/MockUSDC.json
agentopia/api_key.py
agentopia/client.py
agentopia/decorator.py
agentopia/deposit.py
agentopia/hold.py
agentopia/py.typed
agentopia/service.py
agentopia/services/__init__.py
agentopia/services/abi_service.py
agentopia/services/read_service.py
agentopia/services/web3_service.py
agentopia/settings.py
agentopia/utility.py
agentopia-0.1.8.dist-info/LICENSE
agentopia-0.1.8.dist-info/METADATA
agentopia-0.1.8.dist-info/WHEEL
agentopia-0.1.8.dist-info/RECORD
