Metadata-Version: 2.1
Name: agentopia
Version: 0.1.8
Summary: 
Author: Yash Agarwal
Author-email: yash@nurturelabs.co
Requires-Python: >=3.9,<4.0
Classifier: Programming Language :: Python :: 3
Classifier: Programming Language :: Python :: 3.9
Classifier: Programming Language :: Python :: 3.10
Classifier: Programming Language :: Python :: 3.11
Classifier: Programming Language :: Python :: 3.12
Requires-Dist: eth-account (>=0.13.4,<0.14.0)
Requires-Dist: httpx
Requires-Dist: orjson (>=3.10,<4.0)
Requires-Dist: pipe
Requires-Dist: pycryptodome (>=3.21.0,<4.0.0)
Requires-Dist: pydantic-settings (>=2.6,<3.0)
Requires-Dist: python-dateutil (>=2.9,<3.0)
Requires-Dist: requests (>=2.0,<3.0)
Requires-Dist: web3 (>=7.5,<8.0)
